g2p_en_plus/__init__.py
g2p_en_plus/checkpoint20.npz
g2p_en_plus/expand.py
g2p_en_plus/g2p.py
g2p_en_plus/homographs.en
g2p_en_plus-2.0.3.dist-info/LICENSE.txt
g2p_en_plus-2.0.3.dist-info/METADATA
g2p_en_plus-2.0.3.dist-info/WHEEL
g2p_en_plus-2.0.3.dist-info/top_level.txt
g2p_en_plus-2.0.3.dist-info/RECORD
