Metadata-Version: 2.1
Name: g2p_en_plus
Version: 2.0.3
Summary: A Simple Python Module for English Grapheme To Phoneme Conversion
Author: Kyubyong Park & Jongseok Kim, Modified by Myron
Author-email: kbpark.linguist@gmail.com
License: Apache Software License
Keywords: g2p,g2p_en,g2p_en_plus
License-File: LICENSE.txt
Requires-Dist: numpy >=1.13.1
Requires-Dist: nltk >=3.2.4
Requires-Dist: inflect >=0.3.1
Requires-Dist: distance >=0.1.3
